{
    "formInfo":{
        "formName":"goal-setting-step1",
        "Data":[
            {
                "displayText": "New Business Income",
                "type": "TEXT",
                "inputName": "new_business_income",
                "isRequired": "Y",
                "maxLength": 20,
                "isReadOnly": "N",
                "value":"",
                "placeholder": "Type here...",
                "checkboxOnlyLeaf": false, 
                "datas": [],
                "triggers": [],
                "option": []
            },
            {
                "displayText": "FYC",
                "type": "TEXT",
                "inputName": "fyc",
                "isRequired": "Y",
                "maxLength": 20,
                "isReadOnly": "N",
                "value":"",
                "placeholder": "Type here...",
                "checkboxOnlyLeaf": false, 
                "datas": [],
                "triggers": [],
                "option": []
            },
            {
                "displayText": "Annual Convention",
                "type": "SELECT",
                "inputName": "annual_convention",
                "isRequired": "Y",
                "maxLength": 99999,
                "isReadOnly": "N",
                "value":"",
                "placeholder": "Select",
                "checkboxOnlyLeaf": false, 
                "datas": [],
                "triggers": [],
                "option": [
                    {
                      "key": "1",
                      "value": "Option 1"
                    },
                    {
                      "key": "2",
                      "value": "Option 2"
                    },
                    {
                      "key": "3",
                      "value": "Option 3"    
                    }
                ]
            },
            {
                "displayText": "Trade assaciation",
                "type": "SELECT",
                "inputName": "trade_assaciation",
                "isRequired": "Y",
                "maxLength": 99999,
                "isReadOnly": "N",
                "placeholder": "Select",
                "value":"",
                "checkboxOnlyLeaf": false, 
                "datas": [],
                "triggers": [],
                "option": [
                    {
                      "key": "1",
                      "value": "Op1"
                    },
                    {
                      "key": "2",
                      "value": "Op2"
                    },
                    {
                      "key": "3",
                      "value": "Op3"    
                    }
                ]
            }

        ]
    }
}